[{"name":"arme"},{"name":"exposer"},{"name":"fagot"},{"name":"renoncer"},{"name":"violette"},{"name":"honnête"},{"name":"environ"},{"name":"remonter"},{"name":"aboyer"},{"name":"arroser"},{"name":"manœuvrer"},{"name":"sécurité"},{"name":"destination"},{"name":"empresser"},{"name":"partage"},{"name":"contenu"},{"name":"héros"},{"name":"grandeur"},{"name":"employé"},{"name":"fond"},{"name":"espoir"},{"name":"coller"},{"name":"miroir"},{"name":"méchant"},{"name":"durement"},{"name":"délice"},{"name":"élève"},{"name":"essayer"},{"name":"base"},{"name":"théâtre"},{"name":"ici"},{"name":"sévèrement"},{"name":"exposition"},{"name":"taire"},{"name":"épargner"},{"name":"parole"},{"name":"cage"},{"name":"serrer"},{"name":"observation"},{"name":"respiration"},{"name":"punition"},{"name":"poulain"},{"name":"chanter"},{"name":"port"},{"name":"remarque"},{"name":"accomplir"},{"name":"buis"},{"name":"débiter"},{"name":"culture"},{"name":"mer"},{"name":"totalement"},{"name":"enterrement"},{"name":"crime"},{"name":"laborieux"},{"name":"chef"},{"name":"énerver"},{"name":"pelouse"},{"name":"suffisant"},{"name":"honneur"},{"name":"ordre"},{"name":"comparaison"},{"name":"voter"},{"name":"sangloter"},{"name":"pendre"},{"name":"terre"},{"name":"questionner"},{"name":"destinée"},{"name":"maussade"},{"name":"coton"},{"name":"ravin"},{"name":"cimetière"},{"name":"silencieux"},{"name":"chapeau"},{"name":"paix"},{"name":"fabrique"},{"name":"redouter"},{"name":"consolant"},{"name":"colorer"},{"name":"description"},{"name":"gratitude"},{"name":"nappe"},{"name":"antérieur"},{"name":"précaution"},{"name":"arrêt"},{"name":"verdure"},{"name":"avouer"},{"name":"cloison"},{"name":"surveillance"},{"name":"profondément"},{"name":"musique"},{"name":"accrocher"},{"name":"obscurité"},{"name":"but"},{"name":"régime"},{"name":"sept"},{"name":"roi"},{"name":"superficiel"},{"name":"soulager"},{"name":"éveiller"},{"name":"prospérité"},{"name":"tromper"},{"name":"averse"},{"name":"folie"},{"name":"règne"},{"name":"marguerite"},{"name":"goutte"},{"name":"vendeur"},{"name":"désoler"},{"name":"orgueilleux"},{"name":"quand"},{"name":"coucou"},{"name":"fin"},{"name":"affectueusement"},{"name":"loup"},{"name":"degré"},{"name":"transformer"},{"name":"obligation"},{"name":"novembre"},{"name":"constater"},{"name":"vacances"},{"name":"phrase"},{"name":"occupant"},{"name":"naturellement"},{"name":"comprendre"},{"name":"remuer"},{"name":"analyse"},{"name":"ruisseler"},{"name":"découper"},{"name":"siffler"},{"name":"commande"},{"name":"file"},{"name":"recherche"},{"name":"animal"},{"name":"appareil"},{"name":"gilet"},{"name":"jaune"},{"name":"empêcher"},{"name":"direction"},{"name":"colonel"},{"name":"niche"},{"name":"billet"},{"name":"gémir"},{"name":"enflammer"},{"name":"assurance"},{"name":"phare"},{"name":"poursuite"},{"name":"sud"},{"name":"accueil"},{"name":"quatrième"},{"name":"content"},{"name":"fier"},{"name":"sac"},{"name":"horizontal"},{"name":"installer"},{"name":"luxe"},{"name":"promettre"},{"name":"corbeau"},{"name":"faire"},{"name":"étaler"},{"name":"plaisir"},{"name":"répondre"},{"name":"lance"},{"name":"agiter"},{"name":"changement"},{"name":"couvert"},{"name":"course"},{"name":"délicieux"},{"name":"fusée"},{"name":"obscurcir"},{"name":"onde"},{"name":"blanc"},{"name":"cas"},{"name":"parapluie"},{"name":"étendre"},{"name":"carnet"},{"name":"juger"},{"name":"pourrir"},{"name":"ranimer"},{"name":"hier"},{"name":"renseignement"},{"name":"préférence"},{"name":"travailler"},{"name":"duc"},{"name":"envoi"},{"name":"foin"},{"name":"affaiblir"},{"name":"généralement"},{"name":"désireux"},{"name":"vêtir"},{"name":"sécher"},{"name":"mûr"},{"name":"vingt"},{"name":"quai"},{"name":"erreur"},{"name":"travers"},{"name":"de"},{"name":"autoriser"},{"name":"balai"},{"name":"arriver"},{"name":"promener"},{"name":"griffe"},{"name":"exister"},{"name":"papillon"},{"name":"circuler"},{"name":"manœuvre"},{"name":"auberge"},{"name":"écraser"},{"name":"bassin"},{"name":"ouvrier"},{"name":"poutre"},{"name":"hypocrite"},{"name":"dizaine"},{"name":"sang"},{"name":"insigne"},{"name":"adversaire"},{"name":"chevalier"},{"name":"queue"},{"name":"division"},{"name":"artiste"},{"name":"album"},{"name":"chaux"},{"name":"cinq"},{"name":"taille"},{"name":"soulagement"},{"name":"âgé"},{"name":"triple"},{"name":"être"},{"name":"photographe"},{"name":"résoudre"},{"name":"infirme"},{"name":"émission"},{"name":"marin"},{"name":"tâcher"},{"name":"cacher"},{"name":"gris"},{"name":"coudre"},{"name":"institutrice"},{"name":"lecture"},{"name":"endosser"},{"name":"combattre"},{"name":"cuir"},{"name":"morne"},{"name":"attentif"},{"name":"trente"},{"name":"donner"},{"name":"massif"},{"name":"sillon"},{"name":"nez"},{"name":"calcaire"},{"name":"bijoutier"},{"name":"système"},{"name":"dur"},{"name":"distrait"},{"name":"quotidien"},{"name":"redescendre"},{"name":"charitable"},{"name":"fête"},{"name":"collier"},{"name":"rentrer"},{"name":"automobile"},{"name":"baignoire"},{"name":"boue"},{"name":"cime"},{"name":"revivre"},{"name":"guetter"},{"name":"constamment"},{"name":"épaule"},{"name":"arête"},{"name":"ardent"},{"name":"gland"},{"name":"défilé"},{"name":"projet"},{"name":"fonction"},{"name":"acier"},{"name":"craintif"},{"name":"rassembler"},{"name":"tranquillement"},{"name":"sublime"},{"name":"incident"},{"name":"science"},{"name":"parvenir"},{"name":"utilisation"},{"name":"roche"},{"name":"soudain"},{"name":"piéton"},{"name":"bourrasque"},{"name":"paisible"},{"name":"boire"},{"name":"gracieux"},{"name":"instant"},{"name":"déshabiller"},{"name":"tendrement"},{"name":"incendie"},{"name":"gronder"},{"name":"composition"},{"name":"compléter"},{"name":"retourner"},{"name":"emplacement"},{"name":"autorisation"},{"name":"pommier"},{"name":"coupable"},{"name":"grâce"},{"name":"maigrir"},{"name":"air"},{"name":"américain"},{"name":"vaillant"},{"name":"brusquement"},{"name":"couchant"},{"name":"multiplicateur"},{"name":"perspective"},{"name":"livret"},{"name":"menton"},{"name":"présent"},{"name":"sabre"},{"name":"gourmand"},{"name":"juillet"},{"name":"mouvoir"},{"name":"baisser"},{"name":"jouet"},{"name":"serein"},{"name":"république"},{"name":"résumé"},{"name":"maladie"},{"name":"dépôt"},{"name":"tableau"},{"name":"mai"},{"name":"mignon"},{"name":"épée"},{"name":"mouvement"},{"name":"réveil"},{"name":"reculer"},{"name":"contempler"},{"name":"fossé"},{"name":"indépendance"},{"name":"femme"},{"name":"chanteur"},{"name":"sanglot"},{"name":"extraire"},{"name":"empereur"},{"name":"boucler"},{"name":"gonfler"},{"name":"rapidement"},{"name":"balançoire"},{"name":"distinguer"},{"name":"imposant"},{"name":"tendre"},{"name":"résigner"},{"name":"associer"},{"name":"voltiger"},{"name":"brebis"},{"name":"grand"},{"name":"croître"},{"name":"guérison"},{"name":"facile"},{"name":"rosier"},{"name":"local"},{"name":"front"},{"name":"réfectoire"},{"name":"œil"},{"name":"amusant"},{"name":"propriétaire"},{"name":"éternel"},{"name":"multiplication"},{"name":"endroit"},{"name":"chose"},{"name":"lot"},{"name":"livrer"},{"name":"bâtiment"},{"name":"lieu"},{"name":"redoubler"},{"name":"broder"},{"name":"perte"},{"name":"officiel"},{"name":"perfection"},{"name":"os"},{"name":"échantillon"},{"name":"bain"},{"name":"injustice"},{"name":"traverser"},{"name":"sauvage"},{"name":"exécuter"},{"name":"épi"},{"name":"accent"},{"name":"sourd"},{"name":"main"},{"name":"imprimé"},{"name":"écarter"},{"name":"chèvre"},{"name":"luire"},{"name":"timidité"},{"name":"long"},{"name":"moineau"},{"name":"entraînement"},{"name":"arracher"},{"name":"tracer"},{"name":"jeter"},{"name":"automatique"},{"name":"honorable"},{"name":"aveugle"},{"name":"effet"},{"name":"ficelle"},{"name":"chiffre"},{"name":"masquer"},{"name":"fontaine"},{"name":"saisir"},{"name":"pois"},{"name":"clairon"},{"name":"terrain"},{"name":"protéger"},{"name":"déboucher"},{"name":"dissiper"},{"name":"courageux"},{"name":"façon"},{"name":"ceinture"},{"name":"rouler"},{"name":"rarement"},{"name":"lit"},{"name":"enchanté"},{"name":"alentours"},{"name":"anxieux"},{"name":"heureusement"},{"name":"agir"},{"name":"véhicule"},{"name":"foncé"},{"name":"essence"},{"name":"fourche"},{"name":"grogner"},{"name":"mois"},{"name":"nu"},{"name":"brume"},{"name":"dos"},{"name":"étoile"},{"name":"apprêter"},{"name":"appel"},{"name":"ressort"},{"name":"scène"},{"name":"poteau"},{"name":"tir"},{"name":"poison"},{"name":"défaire"},{"name":"sentier"},{"name":"embarrasser"},{"name":"émouvoir"},{"name":"fendre"},{"name":"poudre"},{"name":"chasseur"},{"name":"grange"},{"name":"fréquent"},{"name":"cour"},{"name":"recoucher"},{"name":"sortir"},{"name":"lecteur"},{"name":"économie"},{"name":"traversée"},{"name":"contentement"},{"name":"crainte"},{"name":"régiment"},{"name":"robustesse"},{"name":"pantoufle"},{"name":"exciter"},{"name":"peinture"},{"name":"là-haut"},{"name":"départ"},{"name":"mot"},{"name":"ralentir"},{"name":"touffe"},{"name":"mieux"},{"name":"taquiner"},{"name":"paraître"},{"name":"explication"},{"name":"image"},{"name":"fréquemment"},{"name":"précipiter"},{"name":"bouleverser"},{"name":"bandit"},{"name":"silence"},{"name":"sévère"},{"name":"lunettes"},{"name":"acte"},{"name":"entièrement"},{"name":"jaillir"},{"name":"timide"},{"name":"préparation"},{"name":"conseiller"},{"name":"direct"},{"name":"chaume"},{"name":"sens"},{"name":"sensible"},{"name":"métallique"},{"name":"désobéissance"},{"name":"lisse"},{"name":"surface"},{"name":"rapporter"},{"name":"nord"},{"name":"œil"},{"name":"tourner"},{"name":"besoin"},{"name":"vacances"},{"name":"atteindre"},{"name":"onduler"},{"name":"clouer"},{"name":"atterrir"},{"name":"réfugier"},{"name":"éclatant"},{"name":"dent"},{"name":"minuscule"},{"name":"clair"},{"name":"buisson"},{"name":"descente"},{"name":"prompt"},{"name":"relativement"},{"name":"exact"},{"name":"neige"},{"name":"périr"},{"name":"couver"},{"name":"festin"},{"name":"plusieurs"},{"name":"veine"},{"name":"discussion"},{"name":"refus"},{"name":"reprise"},{"name":"chauffage"},{"name":"vainqueur"},{"name":"triompher"},{"name":"conseil"},{"name":"mécanique"},{"name":"divers"},{"name":"frapper"},{"name":"marche"},{"name":"familier"},{"name":"compliquer"},{"name":"épine"},{"name":"empire"},{"name":"alcool"},{"name":"comptoir"},{"name":"sensationnel"},{"name":"fortement"},{"name":"imaginer"},{"name":"confondre"},{"name":"politesse"},{"name":"combattant"},{"name":"impossible"},{"name":"avoir"},{"name":"quatre"},{"name":"création"},{"name":"pardessus"},{"name":"mûrir"},{"name":"propos"},{"name":"gorge"},{"name":"professeur"},{"name":"organisation"},{"name":"pensionnaire"},{"name":"clavier"},{"name":"disposer"},{"name":"chaîne"},{"name":"poirier"},{"name":"entrain"},{"name":"vase"},{"name":"terriblement"},{"name":"futur"},{"name":"quitter"},{"name":"exemple"},{"name":"bond"},{"name":"colonne"},{"name":"monument"},{"name":"voiler"},{"name":"tenter"},{"name":"cheval"},{"name":"nier"},{"name":"briquet"},{"name":"poussière"},{"name":"production"},{"name":"imprudence"},{"name":"là-bas"},{"name":"geler"},{"name":"hausser"},{"name":"feu"},{"name":"directement"},{"name":"inscription"},{"name":"écrivain"},{"name":"exprimer"},{"name":"héroïque"},{"name":"éclat"},{"name":"éternité"},{"name":"portefeuille"},{"name":"approuver"},{"name":"carte"},{"name":"interroger"},{"name":"seconde"},{"name":"revêtir"},{"name":"successivement"},{"name":"grenouille"},{"name":"bâiller"},{"name":"tailler"},{"name":"étonner"},{"name":"région"},{"name":"désespoir"},{"name":"monseigneur"},{"name":"aimer"},{"name":"mouiller"},{"name":"normal"},{"name":"douter"},{"name":"poumon"},{"name":"distraire"},{"name":"possible"},{"name":"exactement"},{"name":"approche"},{"name":"haleine"},{"name":"bûche"},{"name":"lampe"},{"name":"acquitter"},{"name":"rieur"},{"name":"statue"},{"name":"cité"},{"name":"imposer"},{"name":"lâcher"},{"name":"renvoyer"},{"name":"avare"},{"name":"fâcheux"},{"name":"raser"},{"name":"animation"},{"name":"récréation"},{"name":"miel"},{"name":"illusion"},{"name":"destruction"},{"name":"secrétaire"},{"name":"camion"},{"name":"plage"},{"name":"matinal"},{"name":"décembre"},{"name":"sacrifier"},{"name":"vie"},{"name":"poche"},{"name":"ignorance"},{"name":"ligne"},{"name":"hésiter"},{"name":"bureau"},{"name":"méchanceté"},{"name":"dégager"},{"name":"ronces"},{"name":"réclamer"},{"name":"paire"},{"name":"patte"},{"name":"commander"},{"name":"occasion"},{"name":"enseigner"},{"name":"officier"},{"name":"garnir"},{"name":"échapper"},{"name":"accueillir"},{"name":"intelligence"},{"name":"mélancolie"},{"name":"établissement"},{"name":"cochon"},{"name":"doré"},{"name":"également"},{"name":"de"},{"name":"beauté"},{"name":"étoffe"},{"name":"ventre"},{"name":"faiblesse"},{"name":"intense"},{"name":"recevoir"},{"name":"au-dessus"},{"name":"voleur"},{"name":"opposer"},{"name":"bonheur"},{"name":"palier"},{"name":"troupeau"},{"name":"radieux"},{"name":"or"},{"name":"transparent"},{"name":"août"},{"name":"gaz"},{"name":"intéresser"},{"name":"encombrer"},{"name":"proche"},{"name":"bouquet"},{"name":"démonter"},{"name":"bibliothèque"},{"name":"disparition"},{"name":"somme"},{"name":"poil"},{"name":"suffrage"},{"name":"rattacher"},{"name":"mélodieux"},{"name":"verre"},{"name":"charme"},{"name":"fraîcheur"},{"name":"effrayant"},{"name":"culotte"},{"name":"marine"},{"name":"marquer"},{"name":"léger"},{"name":"patrie"},{"name":"convenir"},{"name":"wagon"},{"name":"habitant"},{"name":"détester"},{"name":"armer"},{"name":"reparaître"},{"name":"régulièrement"},{"name":"orange"},{"name":"reflet"},{"name":"exécution"},{"name":"jalousie"},{"name":"organiser"},{"name":"vigueur"},{"name":"dessiner"},{"name":"marchand"},{"name":"calme"},{"name":"porter"},{"name":"persévérer"},{"name":"propre"},{"name":"lécher"},{"name":"importer"},{"name":"détour"},{"name":"journal"},{"name":"effacer"},{"name":"rêve"},{"name":"longueur"},{"name":"carreau"},{"name":"cruel"},{"name":"enfoncer"},{"name":"coupe"},{"name":"nation"},{"name":"chapitre"},{"name":"courir"},{"name":"danseur"},{"name":"anxiété"},{"name":"gâteau"},{"name":"fourrure"},{"name":"acheminer"},{"name":"quart"},{"name":"copier"},{"name":"drôle"},{"name":"administration"},{"name":"noix"},{"name":"gentil"},{"name":"hanche"},{"name":"brun"},{"name":"siège"},{"name":"énorme"},{"name":"masque"},{"name":"aurore"},{"name":"supérieur"},{"name":"redevenir"},{"name":"pâturage"},{"name":"regret"},{"name":"simplement"},{"name":"cabine"},{"name":"achever"},{"name":"curiosité"},{"name":"avenue"},{"name":"courrier"},{"name":"bataille"},{"name":"croûte"},{"name":"parterre"},{"name":"soulier"},{"name":"fixe"},{"name":"distraction"},{"name":"quinzaine"},{"name":"écorce"},{"name":"distribution"},{"name":"faucher"},{"name":"correct"},{"name":"introduire"},{"name":"diviseur"},{"name":"rue"},{"name":"debout"},{"name":"scolaire"},{"name":"entreprendre"},{"name":"laid"},{"name":"caserne"},{"name":"fiévreux"},{"name":"carré"},{"name":"enterrer"},{"name":"espace"},{"name":"chute"},{"name":"restaurant"},{"name":"humeur"},{"name":"jeudi"},{"name":"respect"},{"name":"solitude"},{"name":"remettre"},{"name":"allonger"},{"name":"rapide"},{"name":"finir"},{"name":"refuge"},{"name":"abords"},{"name":"fleur"},{"name":"capital"},{"name":"flot"},{"name":"barrière"},{"name":"supposer"},{"name":"orage"},{"name":"invisible"},{"name":"personnage"},{"name":"voyager"},{"name":"droite"},{"name":"bière"},{"name":"rhume"},{"name":"cultiver"},{"name":"eau"},{"name":"instrument"},{"name":"certainement"},{"name":"livre"},{"name":"récompense"},{"name":"brin"},{"name":"national"},{"name":"opérer"},{"name":"chant"},{"name":"choc"},{"name":"outil"},{"name":"corne"},{"name":"sérieux"},{"name":"tâche"},{"name":"décharger"},{"name":"obligation"},{"name":"excellent"},{"name":"provisions"},{"name":"renard"},{"name":"bienfaiteur"},{"name":"pire"},{"name":"pâte"},{"name":"profiter"},{"name":"arrêter"},{"name":"colombe"},{"name":"harmonieux"},{"name":"pensée"},{"name":"article"},{"name":"étudiant"},{"name":"apparaître"},{"name":"tabac"},{"name":"monde"},{"name":"rat"},{"name":"endormir"},{"name":"prononcer"},{"name":"pécher"},{"name":"veston"},{"name":"lundi"},{"name":"rejoindre"},{"name":"user"},{"name":"diviser"},{"name":"croiser"},{"name":"redonner"},{"name":"que"},{"name":"ennui"},{"name":"librairie"},{"name":"détruire"},{"name":"oser"},{"name":"cent"},{"name":"noircir"},{"name":"souterrain"},{"name":"voler"},{"name":"risquer"},{"name":"quelquefois"},{"name":"tordre"},{"name":"inégal"},{"name":"tombeau"},{"name":"embarquer"},{"name":"six"},{"name":"aspect"},{"name":"houille"},{"name":"encore"},{"name":"maladroit"},{"name":"passion"},{"name":"penchant"},{"name":"tant"},{"name":"rapport"},{"name":"proposition"},{"name":"cerveau"},{"name":"pinson"},{"name":"sain"},{"name":"rage"},{"name":"chêne"},{"name":"enfin"},{"name":"contenter"},{"name":"marcassin"},{"name":"venger"},{"name":"violence"},{"name":"ingrat"},{"name":"loi"},{"name":"passer"},{"name":"nain"},{"name":"jour"},{"name":"assaut"},{"name":"forestier"},{"name":"épuiser"},{"name":"sueur"},{"name":"rien"},{"name":"doigt"},{"name":"rêver"},{"name":"parfum"},{"name":"désordre"},{"name":"soins"},{"name":"sagesse"},{"name":"FALSE"},{"name":"puissant"},{"name":"juin"},{"name":"cérémonie"},{"name":"extrémité"},{"name":"briller"},{"name":"demain"},{"name":"deux"},{"name":"guêpe"},{"name":"depuis"},{"name":"photographie"},{"name":"trompette"},{"name":"lieue"},{"name":"achat"},{"name":"magique"},{"name":"cire"},{"name":"embarras"},{"name":"dépenser"},{"name":"engagement"},{"name":"protection"},{"name":"débarrasser"},{"name":"battre"},{"name":"après-midi"},{"name":"lilas"},{"name":"renfermer"},{"name":"adresser"},{"name":"produit"},{"name":"cuivre"},{"name":"hache"},{"name":"étude"},{"name":"ivoire"},{"name":"transporter"},{"name":"caractère"},{"name":"bûcheron"},{"name":"doute"},{"name":"débarquer"},{"name":"parfois"},{"name":"princesse"},{"name":"retentir"},{"name":"roseau"},{"name":"cœur"},{"name":"tuer"},{"name":"différent"},{"name":"larme"},{"name":"angoisse"},{"name":"salaire"},{"name":"imiter"},{"name":"aussi"},{"name":"vêtement"},{"name":"utiliser"},{"name":"permettre"},{"name":"multitude"},{"name":"recommencer"},{"name":"an"},{"name":"écolier"},{"name":"labeur"},{"name":"partir"},{"name":"rang"},{"name":"pistolet"},{"name":"victime"},{"name":"claquer"},{"name":"industriel"},{"name":"activité"},{"name":"employer"},{"name":"final"},{"name":"aigu"},{"name":"électricité"},{"name":"unique"},{"name":"incroyable"},{"name":"raconter"},{"name":"baraque"},{"name":"fourmi"},{"name":"allée"},{"name":"chasser"},{"name":"mât"},{"name":"parer"},{"name":"somme"},{"name":"médecin"},{"name":"place"},{"name":"bouton"},{"name":"asseoir"},{"name":"sauter"},{"name":"instruction"},{"name":"épouvanter"},{"name":"bruit"},{"name":"zone"},{"name":"sage"},{"name":"angle"},{"name":"régulier"},{"name":"terminer"},{"name":"blond"},{"name":"calmer"},{"name":"suite"},{"name":"président"},{"name":"millier"},{"name":"maintenir"},{"name":"aventure"},{"name":"élan"},{"name":"vendredi"},{"name":"tournant"},{"name":"menacer"},{"name":"truie"},{"name":"sécant"},{"name":"domaine"},{"name":"malheur"},{"name":"incliner"},{"name":"obéissance"},{"name":"entier"},{"name":"moteur"},{"name":"guérir"},{"name":"durant"},{"name":"cheminée"},{"name":"facteur"},{"name":"renseigner"},{"name":"mystère"},{"name":"falloir"},{"name":"conserver"},{"name":"généreux"},{"name":"culbuter"},{"name":"spectacle"},{"name":"février"},{"name":"barre"},{"name":"cinéma"},{"name":"décider"},{"name":"spécialement"},{"name":"poitrine"},{"name":"abuser"},{"name":"solide"},{"name":"loyal"},{"name":"monstre"},{"name":"tristesse"},{"name":"précéder"},{"name":"besogne"},{"name":"bras"},{"name":"fauve"},{"name":"vulgaire"},{"name":"combat"},{"name":"pile"},{"name":"arbitre"},{"name":"vitesse"},{"name":"inspecteur"},{"name":"soyeux"},{"name":"bœuf"},{"name":"yeux"},{"name":"déranger"},{"name":"introduction"},{"name":"parler"},{"name":"plume"},{"name":"vertu"},{"name":"étendue"},{"name":"sel"},{"name":"ouverture"},{"name":"applaudir"},{"name":"grandiose"},{"name":"suc"},{"name":"neuf"},{"name":"domicile"},{"name":"salade"},{"name":"malin"},{"name":"dérouler"},{"name":"flotter"},{"name":"exprès"},{"name":"scier"},{"name":"abri"},{"name":"dormeur"},{"name":"bloc"},{"name":"maladroitement"},{"name":"expédier"},{"name":"dangereux"},{"name":"vert"},{"name":"poisson"},{"name":"aisé"},{"name":"impression"},{"name":"écouter"},{"name":"électrique"},{"name":"progrès"},{"name":"fleuve"},{"name":"mélange"},{"name":"ample"},{"name":"construire"},{"name":"machine"},{"name":"droit"},{"name":"dentelle"},{"name":"match"},{"name":"bateau"},{"name":"page"},{"name":"vieux"},{"name":"montée"},{"name":"attaquer"},{"name":"corps"},{"name":"aspirer"},{"name":"attentivement"},{"name":"voix"},{"name":"dessus"},{"name":"lugubre"},{"name":"hâte"},{"name":"élégant"},{"name":"conduire"},{"name":"succès"},{"name":"gaieté"},{"name":"état"},{"name":"concert"},{"name":"bougie"},{"name":"bouteille"},{"name":"noir"},{"name":"gravure"},{"name":"pâle"},{"name":"tousser"},{"name":"membre"},{"name":"coq"},{"name":"écrier"},{"name":"marque"},{"name":"vivant"},{"name":"louer"},{"name":"consoler"},{"name":"faveur"},{"name":"bienveillance"},{"name":"ouvrir"},{"name":"balance"},{"name":"tilleul"},{"name":"coin"},{"name":"secousse"},{"name":"esprit"},{"name":"visage"},{"name":"orteil"},{"name":"mansarde"},{"name":"dix"},{"name":"tremblement"},{"name":"calendrier"},{"name":"envoyer"},{"name":"plafond"},{"name":"dire"},{"name":"bonnet"},{"name":"pénible"},{"name":"pitié"},{"name":"cristal"},{"name":"commencement"},{"name":"troupe"},{"name":"comble"},{"name":"indépendant"},{"name":"colère"},{"name":"chocolat"},{"name":"gâter"},{"name":"brusque"},{"name":"ressentiment"},{"name":"crépuscule"},{"name":"dernièrement"},{"name":"poupée"},{"name":"revue"},{"name":"calculer"},{"name":"bétail"},{"name":"musicien"},{"name":"plan"},{"name":"cube"},{"name":"éteindre"},{"name":"gentiment"},{"name":"pendule"},{"name":"torturer"},{"name":"tapisser"},{"name":"séjour"},{"name":"voyage"},{"name":"partie"},{"name":"citer"},{"name":"agréable"},{"name":"placer"},{"name":"apparence"},{"name":"éclair"},{"name":"féliciter"},{"name":"gagner"},{"name":"roue"},{"name":"désert"},{"name":"fantôme"},{"name":"intéressant"},{"name":"mauve"},{"name":"signification"},{"name":"magnifique"},{"name":"estime"},{"name":"porteur"},{"name":"brouter"},{"name":"durcir"},{"name":"conte"},{"name":"abriter"},{"name":"retarder"},{"name":"fenêtre"},{"name":"environner"},{"name":"recommander"},{"name":"sabot"},{"name":"série"},{"name":"château"},{"name":"ardeur"},{"name":"sourcil"},{"name":"chatouiller"},{"name":"armée"},{"name":"laideur"},{"name":"sauver"},{"name":"apercevoir"},{"name":"voiture"},{"name":"pleurer"},{"name":"écureuil"},{"name":"naufrage"},{"name":"tache"},{"name":"soie"},{"name":"poulet"},{"name":"accuser"},{"name":"prévoir"},{"name":"mercredi"},{"name":"rompre"},{"name":"vouloir"},{"name":"raide"},{"name":"hôtel"},{"name":"matelot"},{"name":"contact"},{"name":"flaque"},{"name":"renoncule"},{"name":"franc"},{"name":"mortel"},{"name":"temps"},{"name":"cave"},{"name":"changer"},{"name":"chauffer"},{"name":"jusque"},{"name":"manuel"},{"name":"ingénieur"},{"name":"camper"},{"name":"réussir"},{"name":"argent"},{"name":"midi"},{"name":"plonger"},{"name":"vanter"},{"name":"rédaction"},{"name":"rejeter"},{"name":"contraire"},{"name":"nager"},{"name":"emparer"},{"name":"craquement"},{"name":"lettre"},{"name":"moyenne"},{"name":"chauve"},{"name":"dette"},{"name":"tard"},{"name":"villa"},{"name":"vieillard"},{"name":"école"},{"name":"dossier"},{"name":"tomber"},{"name":"colle"},{"name":"style"},{"name":"condamner"},{"name":"ensoleillé"},{"name":"pain"},{"name":"provenir"},{"name":"repentir"},{"name":"exemplaire"},{"name":"préparer"},{"name":"lanterne"},{"name":"risque"},{"name":"clou"},{"name":"perpendiculaire"},{"name":"automne"},{"name":"sincérité"},{"name":"toilette"},{"name":"cuire"},{"name":"teinte"},{"name":"flamme"},{"name":"signal"},{"name":"atteler"},{"name":"surgir"},{"name":"écurie"},{"name":"intellectuel"},{"name":"sucre"},{"name":"voile"},{"name":"aller"},{"name":"déjà"},{"name":"fruit"},{"name":"cours"},{"name":"régner"},{"name":"horreur"},{"name":"effrayer"},{"name":"époque"},{"name":"période"},{"name":"suave"},{"name":"flanc"},{"name":"tressaillir"},{"name":"sorte"},{"name":"pêcher"},{"name":"dessert"},{"name":"alphabet"},{"name":"profit"},{"name":"multicolore"},{"name":"cesser"},{"name":"merci"},{"name":"chausser"},{"name":"trompeur"},{"name":"plaintif"},{"name":"régler"},{"name":"segment"},{"name":"villageois"},{"name":"porc"},{"name":"absence"},{"name":"pharmacien"},{"name":"brise"},{"name":"communiquer"},{"name":"imprudent"},{"name":"banquier"},{"name":"original"},{"name":"évidemment"},{"name":"bossu"},{"name":"neutre"},{"name":"ordinairement"},{"name":"ferme"},{"name":"orphelin"},{"name":"délicatesse"},{"name":"manche"},{"name":"arbre"},{"name":"isoler"},{"name":"veille"},{"name":"fatiguer"},{"name":"kermesse"},{"name":"couloir"},{"name":"cuisinière"},{"name":"forge"},{"name":"développer"},{"name":"poli"},{"name":"capitale"},{"name":"indifférent"},{"name":"paquet"},{"name":"rapidité"},{"name":"pression"},{"name":"centimètre"},{"name":"revanche"},{"name":"avril"},{"name":"barque"},{"name":"échelle"},{"name":"dîner"},{"name":"affection"},{"name":"ruelle"},{"name":"nerf"},{"name":"campagnard"},{"name":"collège"},{"name":"repasser"},{"name":"balancer"},{"name":"paiement"},{"name":"musée"},{"name":"replier"},{"name":"étouffer"},{"name":"texte"},{"name":"réfléchir"},{"name":"brouillard"},{"name":"recouvrir"},{"name":"enchanter"},{"name":"avance"},{"name":"rêveur"},{"name":"épreuve"},{"name":"imprimerie"},{"name":"moitié"},{"name":"possession"},{"name":"abondant"},{"name":"perdre"},{"name":"obéir"},{"name":"cou"},{"name":"danser"},{"name":"devenir"},{"name":"éblouir"},{"name":"son"},{"name":"humidité"},{"name":"dernier"},{"name":"rond"},{"name":"couronner"},{"name":"souple"},{"name":"réel"},{"name":"lent"},{"name":"pardonner"},{"name":"faim"},{"name":"simplicité"},{"name":"brique"},{"name":"pénétrer"},{"name":"vaincre"},{"name":"journée"},{"name":"tournoyer"},{"name":"adoucir"},{"name":"renaître"},{"name":"franchir"},{"name":"épaisseur"},{"name":"tigresse"},{"name":"tempête"},{"name":"passage"},{"name":"surveiller"},{"name":"intelligent"},{"name":"pan"},{"name":"caverne"},{"name":"tellement"},{"name":"courant"},{"name":"illustrer"},{"name":"dépense"},{"name":"orgue"},{"name":"sitôt"},{"name":"moulin"},{"name":"océan"},{"name":"rôder"},{"name":"inconnu"},{"name":"enfermer"},{"name":"convaincre"},{"name":"moquer"},{"name":"bout"},{"name":"sec"},{"name":"contrarier"},{"name":"quelques"},{"name":"conquérir"},{"name":"frayeur"},{"name":"campagne"},{"name":"propriété"},{"name":"mathématique"},{"name":"creux"},{"name":"compter"},{"name":"réunion"},{"name":"rameau"},{"name":"récompenser"},{"name":"extraordinaire"},{"name":"amuser"},{"name":"royaume"},{"name":"bague"},{"name":"attarder"},{"name":"coude"},{"name":"flûte"},{"name":"défiler"},{"name":"couteau"},{"name":"poste"},{"name":"murmure"},{"name":"rose"},{"name":"mare"},{"name":"brutal"},{"name":"moins"},{"name":"équipe"},{"name":"récit"},{"name":"envahir"},{"name":"mensuel"},{"name":"rappeler"},{"name":"crapaud"},{"name":"aide"},{"name":"notaire"},{"name":"docteur"},{"name":"toujours"},{"name":"mobilier"},{"name":"hésitation"},{"name":"haine"},{"name":"irrégulier"},{"name":"pleurs"},{"name":"centime"},{"name":"méthode"},{"name":"cendre"},{"name":"bracelet"},{"name":"reconnaître"},{"name":"mentir"},{"name":"seigneur"},{"name":"rouge"},{"name":"ramasser"},{"name":"avenir"},{"name":"résister"},{"name":"escalier"},{"name":"coquelicot"},{"name":"nombre"},{"name":"traîner"},{"name":"facilité"},{"name":"créature"},{"name":"trajet"},{"name":"espérer"},{"name":"étonnant"},{"name":"textile"},{"name":"robe"},{"name":"rendre"},{"name":"bien-être"},{"name":"carrousel"},{"name":"demi-heure"},{"name":"émotion"},{"name":"barrage"},{"name":"jardinier"},{"name":"vallon"},{"name":"idiot"},{"name":"flamber"},{"name":"dictionnaire"},{"name":"planer"},{"name":"aviateur"},{"name":"rigoureux"},{"name":"négociant"},{"name":"calcul"},{"name":"bataillon"},{"name":"joyeusement"},{"name":"faiblir"},{"name":"sève"},{"name":"symbole"},{"name":"paupière"},{"name":"lin"},{"name":"bientôt"},{"name":"défaut"},{"name":"guider"},{"name":"cri"},{"name":"symbole"},{"name":"deuxième"},{"name":"réservoir"},{"name":"définitif"},{"name":"poire"},{"name":"ivresse"},{"name":"peintre"},{"name":"oublier"},{"name":"réjouir"},{"name":"modestie"},{"name":"insuffisant"},{"name":"chaise"},{"name":"politique"},{"name":"traversée"},{"name":"doubler"},{"name":"muet"},{"name":"étang"},{"name":"débattre"},{"name":"cependant"},{"name":"représentation"},{"name":"bravo"},{"name":"horrible"},{"name":"persuader"},{"name":"expliquer"},{"name":"mécontent"},{"name":"assiette"},{"name":"trouble"},{"name":"ronde"},{"name":"réclame"},{"name":"sombre"},{"name":"troubler"},{"name":"matière"},{"name":"replacer"},{"name":"formidable"},{"name":"tour"},{"name":"bouche"},{"name":"frais"},{"name":"poignet"},{"name":"autour"},{"name":"grille"},{"name":"malheureusement"},{"name":"branche"},{"name":"actif"},{"name":"demeurer"},{"name":"dictée"},{"name":"dicter"},{"name":"flambeau"},{"name":"goûter"},{"name":"sommet"},{"name":"coiffer"},{"name":"couverture"},{"name":"quinze"},{"name":"faiblement"},{"name":"race"},{"name":"brochure"},{"name":"guide"},{"name":"engager"},{"name":"prétendre"},{"name":"araignée"},{"name":"nettoyer"},{"name":"assistant"},{"name":"toit"},{"name":"muraille"},{"name":"entrée"},{"name":"blessure"},{"name":"explosion"},{"name":"peser"},{"name":"bicyclette"},{"name":"triomphant"},{"name":"gardien"},{"name":"peu"},{"name":"addition"},{"name":"diminuer"},{"name":"corridor"},{"name":"jardin"},{"name":"diamant"},{"name":"seau"},{"name":"force"},{"name":"entretenir"},{"name":"agacer"},{"name":"boucher"},{"name":"vieillir"},{"name":"gelée"},{"name":"enlever"},{"name":"border"},{"name":"prodigieux"},{"name":"heureux"},{"name":"goût"},{"name":"parsemer"},{"name":"attraper"},{"name":"ressource"},{"name":"discours"},{"name":"belge"},{"name":"température"},{"name":"accord"},{"name":"digérer"},{"name":"désagréable"},{"name":"hirondelle"},{"name":"policier"},{"name":"enseignement"},{"name":"correction"},{"name":"attention"},{"name":"vaste"},{"name":"actuellement"},{"name":"entourer"},{"name":"comparable"},{"name":"fromage"},{"name":"informer"},{"name":"suivre"},{"name":"printemps"},{"name":"coquille"},{"name":"chemise"},{"name":"forgeron"},{"name":"perle"},{"name":"soigner"},{"name":"craindre"},{"name":"aplatir"},{"name":"agent"},{"name":"frite"},{"name":"extérieur"},{"name":"piquet"},{"name":"hélas"},{"name":"univers"},{"name":"taxi"},{"name":"égal"},{"name":"museau"},{"name":"retrouver"},{"name":"cesse"},{"name":"habitation"},{"name":"fruitier"},{"name":"trouer"},{"name":"muscle"},{"name":"venir"},{"name":"entrevoir"},{"name":"abaisser"},{"name":"faciliter"},{"name":"prairie"},{"name":"remarquable"},{"name":"revolver"},{"name":"propreté"},{"name":"cinquante"},{"name":"œuf"},{"name":"promenade"},{"name":"ravages"},{"name":"innocence"},{"name":"mal"},{"name":"mesure"},{"name":"vite"},{"name":"disputer"},{"name":"fort"},{"name":"courber"},{"name":"ailleurs"},{"name":"ronfler"},{"name":"savourer"},{"name":"longer"},{"name":"grenier"},{"name":"périlleux"},{"name":"las"},{"name":"classique"},{"name":"cuillère"},{"name":"vigoureux"},{"name":"fixement"},{"name":"plateau"},{"name":"mensonge"},{"name":"conviction"},{"name":"affectueux"},{"name":"casque"},{"name":"salir"},{"name":"clarté"},{"name":"commercial"},{"name":"gendarme"},{"name":"attendre"},{"name":"pinceau"},{"name":"vivre"},{"name":"soleil"},{"name":"regretter"},{"name":"tantôt"},{"name":"chaleur"},{"name":"rallumer"},{"name":"étage"},{"name":"éléphant"},{"name":"boule"},{"name":"dalle"},{"name":"largement"},{"name":"lasser"},{"name":"oubli"},{"name":"alliance"},{"name":"charge"},{"name":"cause"},{"name":"difficulté"},{"name":"canal"},{"name":"clairement"},{"name":"offenser"},{"name":"glissant"},{"name":"hauteur"},{"name":"sortie"},{"name":"ennuyeux"},{"name":"physique"},{"name":"coussin"},{"name":"hêtre"},{"name":"corsage"},{"name":"rayon"},{"name":"lourd"},{"name":"écrire"},{"name":"couler"},{"name":"lieutenant"},{"name":"effroyable"},{"name":"saleté"},{"name":"inerte"},{"name":"acclamation"},{"name":"ci-joint"},{"name":"tas"},{"name":"trouver"},{"name":"amitié"},{"name":"inscrire"},{"name":"bienfaisant"},{"name":"ôter"},{"name":"hêtre"},{"name":"date"},{"name":"bourse"},{"name":"fuite"},{"name":"romain"},{"name":"fameux"},{"name":"attribuer"},{"name":"admirer"},{"name":"faible"},{"name":"continuer"},{"name":"quantité"},{"name":"remède"},{"name":"semer"},{"name":"libre"},{"name":"lendemain"},{"name":"charmant"},{"name":"liberté"},{"name":"barreau"},{"name":"confiance"},{"name":"lamentable"},{"name":"accepter"},{"name":"réputation"},{"name":"péniblement"},{"name":"punir"},{"name":"équilibre"},{"name":"avant"},{"name":"noyer"},{"name":"difficilement"},{"name":"arbuste"},{"name":"piste"},{"name":"source"},{"name":"mobile"},{"name":"division"},{"name":"autant"},{"name":"chat"},{"name":"cueillir"},{"name":"confiture"},{"name":"idéal"},{"name":"respirer"},{"name":"dévouer"},{"name":"lire"},{"name":"verger"},{"name":"invention"},{"name":"paille"},{"name":"violet"},{"name":"redresser"},{"name":"faute"},{"name":"frisson"},{"name":"plus"},{"name":"quoique"},{"name":"regrettable"},{"name":"vent"},{"name":"réellement"},{"name":"préau"},{"name":"préférer"},{"name":"confier"},{"name":"vague"},{"name":"froid"},{"name":"carton"},{"name":"prodiguer"},{"name":"fêter"},{"name":"répétition"},{"name":"communiqué"},{"name":"union"},{"name":"emmener"},{"name":"fuir"},{"name":"pantalon"},{"name":"tranquille"},{"name":"colonie"},{"name":"joueur"},{"name":"secours"},{"name":"côte"},{"name":"procurer"},{"name":"cheveu"},{"name":"dévorer"},{"name":"sommeil"},{"name":"gémissement"},{"name":"boisson"},{"name":"couleur"},{"name":"plomb"},{"name":"retenir"},{"name":"excursion"},{"name":"remords"},{"name":"nouveau"},{"name":"répéter"},{"name":"pardon"},{"name":"dépêcher"},{"name":"fois"},{"name":"pièce"},{"name":"étroit"},{"name":"remercier"},{"name":"collection"},{"name":"réflexion"},{"name":"merveilleusement"},{"name":"glissoire"},{"name":"seize"},{"name":"découvrir"},{"name":"épanouir"},{"name":"fidèle"},{"name":"bleu"},{"name":"relever"},{"name":"mille"},{"name":"champignon"},{"name":"fourneau"},{"name":"limpide"},{"name":"chair"},{"name":"frotter"},{"name":"précis"},{"name":"déjeuner"},{"name":"ornement"},{"name":"inventeur"},{"name":"encre"},{"name":"allumer"},{"name":"ombre"},{"name":"devant"},{"name":"devoir"},{"name":"chaussée"},{"name":"plier"},{"name":"excellence"},{"name":"classe"},{"name":"égarer"},{"name":"alerte"},{"name":"rocher"},{"name":"rentrée"},{"name":"violon"},{"name":"songe"},{"name":"rosée"},{"name":"graine"},{"name":"séance"},{"name":"brigand"},{"name":"vallée"},{"name":"apporter"},{"name":"ruiner"},{"name":"joyeux"},{"name":"fouetter"},{"name":"exigeant"},{"name":"limite"},{"name":"fable"},{"name":"détourner"},{"name":"brûlure"},{"name":"soupirer"},{"name":"légume"},{"name":"tarder"},{"name":"sérieusement"},{"name":"assez"},{"name":"contrarier"},{"name":"message"},{"name":"composer"},{"name":"garantir"},{"name":"sapin"},{"name":"jupon"},{"name":"écran"},{"name":"numéro"},{"name":"cracher"},{"name":"blancheur"},{"name":"entreprise"},{"name":"tonnerre"},{"name":"dimanche"},{"name":"merveille"},{"name":"moment"},{"name":"attaque"},{"name":"saigner"},{"name":"siècle"},{"name":"instituteur"},{"name":"contact"},{"name":"derrière"},{"name":"examiner"},{"name":"brochet"},{"name":"dévouement"},{"name":"boutique"},{"name":"détail"},{"name":"vertical"},{"name":"genou"},{"name":"augmenter"},{"name":"haut"},{"name":"perroquet"},{"name":"perdrix"},{"name":"agile"},{"name":"solitaire"},{"name":"regagner"},{"name":"lac"},{"name":"chaud"},{"name":"abondance"},{"name":"prêter"},{"name":"grêle"},{"name":"janvier"},{"name":"poêle"},{"name":"terreur"},{"name":"plainte"},{"name":"soigneux"},{"name":"assemblée"},{"name":"crème"},{"name":"idée"},{"name":"découverte"},{"name":"ignorer"},{"name":"peut-être"},{"name":"que"},{"name":"fier"},{"name":"ébranler"},{"name":"boucherie"},{"name":"incertain"},{"name":"véritable"},{"name":"différer"},{"name":"vol"},{"name":"oblique"},{"name":"énergique"},{"name":"parfumer"},{"name":"pittoresque"},{"name":"atelier"},{"name":"saut"},{"name":"salon"},{"name":"arrière"},{"name":"ruban"},{"name":"football"},{"name":"pont"},{"name":"aligner"},{"name":"pigeon"},{"name":"chalet"},{"name":"violent"},{"name":"pointe"},{"name":"répartir"},{"name":"dehors"},{"name":"tirer"},{"name":"rampe"},{"name":"trône"},{"name":"soixante"},{"name":"barrer"},{"name":"accourir"},{"name":"occupation"},{"name":"désastre"},{"name":"incapable"},{"name":"situation"},{"name":"gibier"},{"name":"filet"},{"name":"grippe"},{"name":"domestique"},{"name":"carrefour"},{"name":"panache"},{"name":"exiger"},{"name":"essai"},{"name":"tristement"},{"name":"brûlant"},{"name":"annonce"},{"name":"mardi"},{"name":"affectionner"},{"name":"schiste"},{"name":"mémoire"},{"name":"ressentir"},{"name":"bourgmestre"},{"name":"tourbillonner"},{"name":"acteur"},{"name":"hérissé"},{"name":"hasard"},{"name":"portière"},{"name":"acheter"},{"name":"embaumer"},{"name":"franchement"},{"name":"anneau"},{"name":"ordinateur"},{"name":"abondamment"},{"name":"majesté"},{"name":"néanmoins"},{"name":"exercer"},{"name":"thé"},{"name":"caresse"},{"name":"horizon"},{"name":"éprouver"},{"name":"étonnement"},{"name":"déborder"},{"name":"poing"},{"name":"créer"},{"name":"décor"},{"name":"crise"},{"name":"squelette"},{"name":"hâter"},{"name":"amener"},{"name":"ravi"},{"name":"inquiétude"},{"name":"coffre"},{"name":"piège"},{"name":"lancer"},{"name":"promesse"},{"name":"légèrement"},{"name":"cerise"},{"name":"chauffeur"},{"name":"avion"},{"name":"exclamation"},{"name":"moderne"},{"name":"buffet"},{"name":"gazette"},{"name":"œuvre"},{"name":"remise"},{"name":"consolation"},{"name":"casser"},{"name":"piquer"},{"name":"expédition"},{"name":"fonds"},{"name":"guerre"},{"name":"moustique"},{"name":"défunt"},{"name":"protecteur"},{"name":"panorama"},{"name":"orgueil"},{"name":"bonbon"},{"name":"supprimer"},{"name":"voilà"},{"name":"inviter"},{"name":"reporter"},{"name":"pastille"},{"name":"képi"},{"name":"suspendre"},{"name":"pourpre"},{"name":"garage"},{"name":"trimestre"},{"name":"revoir"},{"name":"bousculer"},{"name":"téléphone"},{"name":"rapprocher"},{"name":"précéder"},{"name":"bord"},{"name":"sincèrement"},{"name":"loin"},{"name":"allumette"},{"name":"planche"},{"name":"mode"},{"name":"timbre"},{"name":"salut"},{"name":"camp"},{"name":"pratique"},{"name":"fil"},{"name":"briser"},{"name":"centaine"},{"name":"allure"},{"name":"nid"},{"name":"geste"},{"name":"décoration"},{"name":"modeste"},{"name":"liqueur"},{"name":"encourager"},{"name":"parcourir"},{"name":"vitre"},{"name":"remerciement"},{"name":"français"},{"name":"mouton"},{"name":"subitement"},{"name":"fâcher"},{"name":"sol"},{"name":"murmurer"},{"name":"question"},{"name":"chiffon"},{"name":"élancer"},{"name":"interrogation"},{"name":"plat"},{"name":"arc"},{"name":"champion"},{"name":"conquérant"},{"name":"bête"},{"name":"signe"},{"name":"refermer"},{"name":"conducteur"},{"name":"remporter"},{"name":"grouper"},{"name":"charrue"},{"name":"pluvieux"},{"name":"onze"},{"name":"leçon"},{"name":"emporter"},{"name":"ramener"},{"name":"comparer"},{"name":"sport"},{"name":"sirène"},{"name":"bazar"},{"name":"mettre"},{"name":"néanmoins"},{"name":"ardoise"},{"name":"chevelure"},{"name":"trembler"},{"name":"attrister"},{"name":"préserver"},{"name":"programme"},{"name":"populaire"},{"name":"ballon"},{"name":"couvrir"},{"name":"dater"},{"name":"fièrement"},{"name":"partager"},{"name":"victoire"},{"name":"vélo"},{"name":"planter"},{"name":"mars"},{"name":"exercice"},{"name":"minute"},{"name":"quotient"},{"name":"arranger"},{"name":"locomotive"},{"name":"jacinthe"},{"name":"prolonger"},{"name":"pays"},{"name":"courage"},{"name":"expérience"},{"name":"douze"},{"name":"bénéfice"},{"name":"tentation"},{"name":"foyer"},{"name":"chevreuil"},{"name":"accompagner"},{"name":"merle"},{"name":"naissance"},{"name":"tapis"},{"name":"éducation"},{"name":"implorer"},{"name":"paresse"},{"name":"client"},{"name":"géant"},{"name":"majestueux"},{"name":"mordre"},{"name":"condamné"},{"name":"tonneau"},{"name":"suffisamment"},{"name":"gazouiller"},{"name":"vice"},{"name":"prisonnier"},{"name":"retirer"},{"name":"isométrique"},{"name":"jouir"},{"name":"nature"},{"name":"prix"},{"name":"large"},{"name":"trois"},{"name":"aborder"},{"name":"conscience"},{"name":"ménagère"},{"name":"crâne"},{"name":"quatorze"},{"name":"commission"},{"name":"désespérer"},{"name":"berger"},{"name":"gravir"},{"name":"gros"},{"name":"bienfait"},{"name":"imprévu"},{"name":"ton"},{"name":"impressionner"},{"name":"angle"},{"name":"aiguille"},{"name":"serrure"},{"name":"doux"},{"name":"toile"},{"name":"gerbe"},{"name":"soupir"},{"name":"proclamer"},{"name":"titre"},{"name":"désirer"},{"name":"bourdonner"},{"name":"gland"},{"name":"tiers"},{"name":"probablement"},{"name":"magie"},{"name":"trop"},{"name":"fatigant"},{"name":"annuel"},{"name":"rougir"},{"name":"soldat"},{"name":"inonder"},{"name":"boulanger"},{"name":"garder"},{"name":"vitrine"},{"name":"commandement"},{"name":"choix"},{"name":"manteau"},{"name":"feuille"},{"name":"bavarder"},{"name":"rayonner"},{"name":"sujet"},{"name":"nœud"},{"name":"poilu"},{"name":"pierre"},{"name":"innocent"},{"name":"prince"},{"name":"absolu"},{"name":"matériel"},{"name":"agitation"},{"name":"liquide"},{"name":"mépriser"},{"name":"année"},{"name":"tartine"},{"name":"jadis"},{"name":"circulation"},{"name":"cheville"},{"name":"torture"},{"name":"coquet"},{"name":"cabaret"},{"name":"confus"},{"name":"percer"},{"name":"plein"},{"name":"nouer"},{"name":"poésie"},{"name":"proie"},{"name":"appuyer"},{"name":"ivre"},{"name":"tapisserie"},{"name":"enveloppe"},{"name":"vache"},{"name":"parfum"},{"name":"malheureux"},{"name":"reverdir"},{"name":"lorsque"},{"name":"poulailler"},{"name":"durer"},{"name":"amende"},{"name":"vue"},{"name":"longuement"},{"name":"peindre"},{"name":"combinaison"},{"name":"justice"},{"name":"rideau"},{"name":"aborder"},{"name":"seul"},{"name":"orageux"},{"name":"attrait"},{"name":"chameau"},{"name":"jument"},{"name":"cerisier"},{"name":"purifier"},{"name":"gymnastique"},{"name":"érable"},{"name":"tige"},{"name":"comment"},{"name":"sympathie"},{"name":"paysan"},{"name":"été"},{"name":"nul"},{"name":"soutenir"},{"name":"marquis"},{"name":"commune"},{"name":"cygne"},{"name":"dormir"},{"name":"ingratitude"},{"name":"signature"},{"name":"jugement"},{"name":"enquête"},{"name":"poids"},{"name":"commettre"},{"name":"reprendre"},{"name":"tourmenter"},{"name":"architecte"},{"name":"parure"},{"name":"retard"},{"name":"obliger"},{"name":"abandon"},{"name":"assembler"},{"name":"malle"},{"name":"tremper"},{"name":"expirer"},{"name":"grotte"},{"name":"saison"},{"name":"porc"},{"name":"casquette"},{"name":"oiseau"},{"name":"mince"},{"name":"jouer"},{"name":"suivant"},{"name":"annoncer"},{"name":"estomac"},{"name":"raisonnable"},{"name":"extrême"},{"name":"écouler"},{"name":"surprendre"},{"name":"ensuite"},{"name":"bizarre"},{"name":"expression"},{"name":"gouverner"},{"name":"pente"},{"name":"veau"},{"name":"profession"},{"name":"recourir"},{"name":"lien"},{"name":"peine"},{"name":"œuvre"},{"name":"milieu"},{"name":"nullement"},{"name":"parmi"},{"name":"pipe"},{"name":"recette"},{"name":"eau"},{"name":"aider"},{"name":"désormais"},{"name":"aile"},{"name":"supprimer"},{"name":"patience"},{"name":"lumineux"},{"name":"papier"},{"name":"agneau"},{"name":"artificiel"},{"name":"prochain"},{"name":"relire"},{"name":"pension"},{"name":"anglais"},{"name":"précédent"},{"name":"meilleur"},{"name":"peau"},{"name":"souffle"},{"name":"soirée"},{"name":"tranquillité"},{"name":"analyser"},{"name":"menteur"},{"name":"bleuet"},{"name":"abîmer"},{"name":"serpent"},{"name":"géranium"},{"name":"maigre"},{"name":"objet"},{"name":"général"},{"name":"maudire"},{"name":"volet"},{"name":"disparaître"},{"name":"grève"},{"name":"costume"},{"name":"médecine"},{"name":"peiner"},{"name":"médaille"},{"name":"davantage"},{"name":"tuyau"},{"name":"fondre"},{"name":"caoutchouc"},{"name":"allemand"},{"name":"compliment"},{"name":"fermer"},{"name":"empoisonner"},{"name":"végétal"},{"name":"mouche"},{"name":"célébrer"},{"name":"gloire"},{"name":"vraiment"},{"name":"banc"},{"name":"inquiéter"},{"name":"justement"},{"name":"trait"},{"name":"peuplier"},{"name":"cadre"},{"name":"appui"},{"name":"enthousiasme"},{"name":"pourquoi"},{"name":"ruine"},{"name":"cordial"},{"name":"couturière"},{"name":"table"},{"name":"affreux"},{"name":"proposer"},{"name":"photo"},{"name":"seulement"},{"name":"déclarer"},{"name":"bas"},{"name":"conséquence"},{"name":"chêne"},{"name":"témoin"},{"name":"envelopper"},{"name":"tranchant"},{"name":"laboureur"},{"name":"étirer"},{"name":"rôle"},{"name":"assister"},{"name":"paletot"},{"name":"kilomètre"},{"name":"repousser"},{"name":"navire"},{"name":"lion"},{"name":"salé"},{"name":"descendre"},{"name":"consulter"},{"name":"rattraper"},{"name":"barbu"},{"name":"dominer"},{"name":"plaire"},{"name":"coûteux"},{"name":"semblable"},{"name":"ver"},{"name":"vigne"},{"name":"marchandise"},{"name":"rangée"},{"name":"chagrin"},{"name":"bande"},{"name":"intervenir"},{"name":"dimension"},{"name":"lier"},{"name":"population"},{"name":"porte"},{"name":"règle"},{"name":"transport"},{"name":"quelconque"},{"name":"empressement"},{"name":"conférence"},{"name":"trancher"},{"name":"frissonner"},{"name":"gratuit"},{"name":"village"},{"name":"horloge"},{"name":"curieux"},{"name":"fortune"},{"name":"clairière"},{"name":"dessous"},{"name":"joli"},{"name":"portrait"},{"name":"représentant"},{"name":"azur"},{"name":"efforcer"},{"name":"entendre"},{"name":"profond"},{"name":"primevère"},{"name":"court"},{"name":"brute"},{"name":"caisse"},{"name":"rivière"},{"name":"étalage"},{"name":"usage"},{"name":"mâchoire"},{"name":"vendre"},{"name":"petit"},{"name":"filer"},{"name":"offre"},{"name":"permission"},{"name":"racine"},{"name":"diriger"},{"name":"degré"},{"name":"trésor"},{"name":"fusiller"},{"name":"tendresse"},{"name":"dedans"},{"name":"pincer"},{"name":"ambulance"},{"name":"gazon"},{"name":"multiplier"},{"name":"fabriquer"},{"name":"buveur"},{"name":"cabane"},{"name":"rechercher"},{"name":"inconvénient"},{"name":"souvenir"},{"name":"barbe"},{"name":"début"},{"name":"stupide"},{"name":"fleurir"},{"name":"produire"},{"name":"tabouret"},{"name":"renouveler"},{"name":"avancer"},{"name":"souverain"},{"name":"promptement"},{"name":"gare"},{"name":"aire"},{"name":"perpétuel"},{"name":"manque"},{"name":"rétablir"},{"name":"écrit"},{"name":"vider"},{"name":"impossibilité"},{"name":"lait"},{"name":"affliger"},{"name":"distinction"},{"name":"pareil"},{"name":"provoquer"},{"name":"nourrir"},{"name":"astre"},{"name":"humide"},{"name":"firmament"},{"name":"transmettre"},{"name":"beurre"},{"name":"grimper"},{"name":"constituer"},{"name":"remarquer"},{"name":"occuper"},{"name":"accident"},{"name":"revenir"},{"name":"lièvre"},{"name":"cervelle"},{"name":"torrent"},{"name":"bavard"},{"name":"avertir"},{"name":"travailleur"},{"name":"fournir"},{"name":"obscur"},{"name":"remplir"},{"name":"dessin"},{"name":"humain"},{"name":"poule"},{"name":"matelas"},{"name":"vierge"},{"name":"continuel"},{"name":"défendre"},{"name":"tribunal"},{"name":"parfait"},{"name":"facilement"},{"name":"grandiose"},{"name":"coûter"},{"name":"écrouler"},{"name":"écho"},{"name":"excuser"},{"name":"vaisselle"},{"name":"satisfaction"},{"name":"parc"},{"name":"payer"},{"name":"conduite"},{"name":"conclure"},{"name":"blesser"},{"name":"tenue"},{"name":"laisser"},{"name":"imitation"},{"name":"priver"},{"name":"bal"},{"name":"réserve"},{"name":"valoir"},{"name":"moustache"},{"name":"portée"},{"name":"instruire"},{"name":"gravement"},{"name":"phoque"},{"name":"déchaîner"},{"name":"bulletin"},{"name":"émeraude"},{"name":"joncher"},{"name":"mener"},{"name":"pouvoir"},{"name":"flatter"},{"name":"mauvais"},{"name":"rez-de-chaussée"},{"name":"choisir"},{"name":"mérite"},{"name":"boueux"},{"name":"samedi"},{"name":"prudemment"},{"name":"gouvernement"},{"name":"terrestre"},{"name":"construction"},{"name":"majestueux"},{"name":"féroce"},{"name":"secouer"},{"name":"douloureux"},{"name":"sot"},{"name":"jaunir"},{"name":"réchauffer"},{"name":"pavé"},{"name":"proprement"},{"name":"déplaire"},{"name":"élargir"},{"name":"demande"},{"name":"obéissant"},{"name":"plante"},{"name":"songer"},{"name":"tourbillon"},{"name":"surmonter"},{"name":"cadavre"},{"name":"nourriture"},{"name":"drap"},{"name":"traiter"},{"name":"neiger"},{"name":"mineur"},{"name":"fixer"},{"name":"champ"},{"name":"plaindre"},{"name":"tiroir"},{"name":"soupçonner"},{"name":"connaître"},{"name":"récolter"},{"name":"militaire"},{"name":"contribuer"},{"name":"bien"},{"name":"impatient"},{"name":"manufacture"},{"name":"gazouillement"},{"name":"téléphoner"},{"name":"canon"},{"name":"bise"},{"name":"défaite"},{"name":"pied"},{"name":"entraîner"},{"name":"aviation"},{"name":"entrepreneur"},{"name":"refaire"},{"name":"colis"},{"name":"train"},{"name":"admettre"},{"name":"ordonner"},{"name":"foulard"},{"name":"essuyer"},{"name":"prouver"},{"name":"baguette"},{"name":"refuser"},{"name":"flèche"},{"name":"grondement"},{"name":"maire"},{"name":"seuil"},{"name":"équipage"},{"name":"loisirs"},{"name":"crêpe"},{"name":"imprimer"},{"name":"nombreux"},{"name":"entrer"},{"name":"avantage"},{"name":"chaumière"},{"name":"étoilé"},{"name":"part"},{"name":"inondation"},{"name":"doucement"},{"name":"charbon"},{"name":"retomber"},{"name":"ravissant"},{"name":"fée"},{"name":"ensemble"},{"name":"souffler"},{"name":"écluse"},{"name":"peste"},{"name":"passager"},{"name":"bombardement"},{"name":"habituel"},{"name":"nuisible"},{"name":"problème"},{"name":"réveiller"},{"name":"puissance"},{"name":"professeur"},{"name":"signaler"},{"name":"interdire"},{"name":"signifier"},{"name":"foie"},{"name":"lutte"},{"name":"santé"},{"name":"réciter"},{"name":"joindre"},{"name":"cerf"},{"name":"agricole"},{"name":"désigner"},{"name":"favoriser"},{"name":"botte"},{"name":"splendeur"},{"name":"fouiller"},{"name":"chien"},{"name":"gigantesque"},{"name":"unité"},{"name":"minuit"},{"name":"rustique"},{"name":"grossier"},{"name":"limiter"},{"name":"avocat"},{"name":"escadron"},{"name":"deuil"},{"name":"homme"},{"name":"sonnerie"},{"name":"mur"},{"name":"caprice"},{"name":"trou"},{"name":"certes"},{"name":"grammaire"},{"name":"jurer"},{"name":"chemin"},{"name":"réserver"},{"name":"spectateur"},{"name":"trotter"},{"name":"heure"},{"name":"immobile"},{"name":"robuste"},{"name":"prudence"},{"name":"trace"},{"name":"âne"},{"name":"viser"},{"name":"refus"},{"name":"boucle"},{"name":"entasser"},{"name":"flatteur"},{"name":"odeur"},{"name":"indigne"},{"name":"cuisine"},{"name":"sembler"},{"name":"orchestre"},{"name":"bagages"},{"name":"appartenir"},{"name":"mériter"},{"name":"fourrer"},{"name":"mont"},{"name":"clochette"},{"name":"éclaircir"},{"name":"aéroport"},{"name":"preuve"},{"name":"marronnier"},{"name":"fer"},{"name":"distribuer"},{"name":"procéder"},{"name":"verser"},{"name":"application"},{"name":"générosité"},{"name":"aucun"},{"name":"capitaine"},{"name":"kilogramme"},{"name":"participer"},{"name":"abattre"},{"name":"poignée"},{"name":"précisément"},{"name":"imperméable"},{"name":"affiche"},{"name":"action"},{"name":"souvent"},{"name":"géographie"},{"name":"débris"},{"name":"disperser"},{"name":"baigner"},{"name":"auprès"},{"name":"pointu"},{"name":"attacher"},{"name":"demeure"},{"name":"canne"},{"name":"communal"},{"name":"lever"},{"name":"noyau"},{"name":"pur"},{"name":"acheteur"},{"name":"fabrication"},{"name":"bourgeon"},{"name":"conservation"},{"name":"repartir"},{"name":"tenir"},{"name":"poireau"},{"name":"joie"},{"name":"poursuivre"},{"name":"exquis"},{"name":"loger"},{"name":"girafe"},{"name":"agréablement"},{"name":"bouger"},{"name":"protester"},{"name":"télévision"},{"name":"moral"},{"name":"particulièrement"},{"name":"privation"},{"name":"négligence"},{"name":"exhaler"},{"name":"absolument"},{"name":"sanglier"},{"name":"cuisse"},{"name":"cercle"},{"name":"germer"},{"name":"étourdi"},{"name":"nettement"},{"name":"canard"},{"name":"ruisseau"},{"name":"éclater"},{"name":"friandise"},{"name":"prise"},{"name":"hérisson"},{"name":"confrère"},{"name":"passé"},{"name":"résolution"},{"name":"envoler"},{"name":"immense"},{"name":"bruyant"},{"name":"avant-hier"},{"name":"enrichir"},{"name":"organe"},{"name":"multiplicande"},{"name":"résolution"},{"name":"examen"},{"name":"rare"},{"name":"calmement"},{"name":"reproche"},{"name":"ennemi"},{"name":"ranger"},{"name":"flamand"},{"name":"librement"},{"name":"préférable"},{"name":"frémir"},{"name":"pressé"},{"name":"écaille"},{"name":"jet"},{"name":"mine"},{"name":"blouse"},{"name":"manquer"},{"name":"moisson"},{"name":"nerveux"},{"name":"brouillon"},{"name":"gratter"},{"name":"connaissance"},{"name":"raisin"},{"name":"singe"},{"name":"grossir"},{"name":"histoire"},{"name":"panier"},{"name":"aussitôt"},{"name":"témoigner"},{"name":"présence"},{"name":"lenteur"},{"name":"sacrifice"},{"name":"étable"},{"name":"retrousser"},{"name":"valet"},{"name":"bonne"},{"name":"résultat"},{"name":"échanger"},{"name":"maint"},{"name":"éblouissant"},{"name":"négation"},{"name":"abîme"},{"name":"furieux"},{"name":"représenter"},{"name":"conduite"},{"name":"satin"},{"name":"agréer"},{"name":"pluie"},{"name":"plaie"},{"name":"amer"},{"name":"autre"},{"name":"splendide"},{"name":"auteur"},{"name":"âge"},{"name":"éloigner"},{"name":"corriger"},{"name":"garantie"},{"name":"révision"},{"name":"utilité"},{"name":"longtemps"},{"name":"tôt"},{"name":"pêche"},{"name":"déception"},{"name":"premier"},{"name":"superbe"},{"name":"sûrement"},{"name":"modèle"},{"name":"cahier"},{"name":"encadrer"},{"name":"monnaie"},{"name":"lutter"},{"name":"défense"},{"name":"tranche"},{"name":"finalement"},{"name":"marcher"},{"name":"multiple"},{"name":"capuchon"},{"name":"passe"},{"name":"sinistre"},{"name":"bébé"},{"name":"centre"},{"name":"envie"},{"name":"muguet"},{"name":"hangar"},{"name":"fouet"},{"name":"central"},{"name":"trottoir"},{"name":"invitation"},{"name":"simple"},{"name":"estimer"},{"name":"interruption"},{"name":"capable"},{"name":"betterave"},{"name":"complètement"},{"name":"mèche"},{"name":"solliciter"},{"name":"poser"},{"name":"soulever"},{"name":"barrer"},{"name":"galerie"},{"name":"ville"},{"name":"lisière"},{"name":"énergie"},{"name":"gant"},{"name":"sentiment"},{"name":"mélanger"},{"name":"jonquille"},{"name":"ignorant"},{"name":"glacer"},{"name":"montre"},{"name":"digne"},{"name":"brave"},{"name":"parti"},{"name":"considérable"},{"name":"obstacle"},{"name":"voie"},{"name":"dépouiller"},{"name":"tambour"},{"name":"œillet"},{"name":"demi"},{"name":"rusé"},{"name":"comte"},{"name":"foire"},{"name":"autorité"},{"name":"jamais"},{"name":"pêcheur"},{"name":"approcher"},{"name":"congé"},{"name":"tournée"},{"name":"tulipe"},{"name":"reconnaissant"},{"name":"délivrer"},{"name":"crever"},{"name":"attester"},{"name":"ampoule"},{"name":"graisse"},{"name":"supporter"},{"name":"danse"},{"name":"sou"},{"name":"tête"},{"name":"chevet"},{"name":"favorable"},{"name":"arrondir"},{"name":"ancien"},{"name":"aliment"},{"name":"préparatifs"},{"name":"accabler"},{"name":"amateur"},{"name":"aisément"},{"name":"charité"},{"name":"déplacer"},{"name":"découragement"},{"name":"charger"},{"name":"chandelle"},{"name":"borne"},{"name":"hurler"},{"name":"interrompre"},{"name":"bonhomme"},{"name":"utile"},{"name":"remplacer"},{"name":"colonial"},{"name":"libérer"},{"name":"blé"},{"name":"existence"},{"name":"meule"},{"name":"femelle"},{"name":"lèvre"},{"name":"nuit"},{"name":"fantastique"},{"name":"atmosphère"},{"name":"mort"},{"name":"haie"},{"name":"exception"},{"name":"savant"},{"name":"graver"},{"name":"blessé"},{"name":"souffrance"},{"name":"chaussette"},{"name":"insupportable"},{"name":"lune"},{"name":"corde"},{"name":"précision"},{"name":"imagination"},{"name":"parallèle"},{"name":"fumée"},{"name":"laine"},{"name":"enfouir"},{"name":"révéler"},{"name":"urgent"},{"name":"tasse"},{"name":"individu"},{"name":"entretien"},{"name":"élastique"},{"name":"bon"},{"name":"rassurer"},{"name":"moindre"},{"name":"fléau"},{"name":"chéri"},{"name":"réparer"},{"name":"plaisir"},{"name":"rester"},{"name":"addition"},{"name":"tente"},{"name":"blanchir"},{"name":"illustré"},{"name":"échange"},{"name":"chérir"},{"name":"volume"},{"name":"frontière"},{"name":"voici"},{"name":"reine"},{"name":"chambre"},{"name":"reconnaissable"},{"name":"délaisser"},{"name":"végétation"},{"name":"sentir"},{"name":"vérifier"},{"name":"passif"},{"name":"langue"},{"name":"douzaine"},{"name":"établir"},{"name":"répandre"},{"name":"fermier"},{"name":"souffrir"},{"name":"désolation"},{"name":"sincère"},{"name":"mourir"},{"name":"succéder"},{"name":"distance"},{"name":"moyen"},{"name":"ménage"},{"name":"toutefois"},{"name":"terrible"},{"name":"illuminer"},{"name":"acheminer"},{"name":"soigneusement"},{"name":"constant"},{"name":"reconnaissance"},{"name":"intérieur"},{"name":"espérance"},{"name":"prendre"},{"name":"menu"},{"name":"huile"},{"name":"épicier"},{"name":"valise"},{"name":"sucré"},{"name":"toucher"},{"name":"redire"},{"name":"appartement"},{"name":"infiniment"},{"name":"épouvantable"},{"name":"resplendir"},{"name":"secourir"},{"name":"mètre"},{"name":"nuage"},{"name":"liste"},{"name":"danger"},{"name":"paroi"},{"name":"réaliser"},{"name":"repos"},{"name":"prêt"},{"name":"glace"},{"name":"figure"},{"name":"galoper"},{"name":"autrement"},{"name":"cigarette"},{"name":"rein"},{"name":"zèbre"},{"name":"reste"},{"name":"apparition"},{"name":"indication"},{"name":"journalier"},{"name":"veiller"},{"name":"puits"},{"name":"balle"},{"name":"colline"},{"name":"agriculture"},{"name":"parfaitement"},{"name":"évanouir"},{"name":"redoutable"},{"name":"adieu"},{"name":"fièvre"},{"name":"rire"},{"name":"commerce"},{"name":"total"},{"name":"station"},{"name":"lambeau"},{"name":"projeter"},{"name":"espèce"},{"name":"tram"},{"name":"camarade"},{"name":"habiter"},{"name":"négliger"},{"name":"élégamment"},{"name":"drapeau"},{"name":"hache"},{"name":"grelotter"},{"name":"savoir"},{"name":"durée"},{"name":"dommage"},{"name":"sonnette"},{"name":"pousser"},{"name":"fureur"},{"name":"émerveiller"},{"name":"opération"},{"name":"embellir"},{"name":"obligatoire"},{"name":"amusement"},{"name":"suer"},{"name":"ciseaux"},{"name":"bâtir"},{"name":"tortue"},{"name":"valeur"},{"name":"messagère"},{"name":"frisson"},{"name":"lors"},{"name":"admirable"},{"name":"dague"},{"name":"métallurgie"},{"name":"hameçon"},{"name":"niveau"},{"name":"démontrer"},{"name":"renverser"},{"name":"envier"},{"name":"attachement"},{"name":"désir"},{"name":"flacon"},{"name":"sonore"},{"name":"compte"},{"name":"détendre"},{"name":"lierre"},{"name":"qualité"},{"name":"poète"},{"name":"talent"},{"name":"réduire"},{"name":"contrée"},{"name":"mourant"},{"name":"point"},{"name":"ministre"},{"name":"récolte"},{"name":"aigle"},{"name":"vente"},{"name":"forcer"},{"name":"humble"},{"name":"roux"},{"name":"corolle"},{"name":"gras"},{"name":"déployer"},{"name":"physionomie"},{"name":"ferrer"},{"name":"mousse"},{"name":"ténèbres"},{"name":"appétit"},{"name":"correspondance"},{"name":"respectueux"},{"name":"réussite"},{"name":"retenue"},{"name":"proverbe"},{"name":"balcon"},{"name":"rude"},{"name":"mélodie"},{"name":"soustraction"},{"name":"pirate"},{"name":"primaire"},{"name":"lointain"},{"name":"promeneur"},{"name":"cavalier"},{"name":"condition"},{"name":"posséder"},{"name":"détacher"},{"name":"mallette"},{"name":"grandir"},{"name":"tailleur"},{"name":"craquer"},{"name":"plaine"},{"name":"décourager"},{"name":"hôpital"},{"name":"jeune"},{"name":"reposer"},{"name":"engloutir"},{"name":"franchise"},{"name":"habit"},{"name":"chance"},{"name":"service"},{"name":"tort"},{"name":"note"},{"name":"pâté"},{"name":"mesurer"},{"name":"feuillage"},{"name":"chercher"},{"name":"directeur"},{"name":"chasse"},{"name":"richesse"},{"name":"beaucoup"},{"name":"mécanicien"},{"name":"savoureux"},{"name":"écriture"},{"name":"caresser"},{"name":"étincelant"},{"name":"situer"},{"name":"cultivateur"},{"name":"TRUE"},{"name":"franc"},{"name":"travail"},{"name":"semaine"},{"name":"ferraille"},{"name":"zèle"},{"name":"quarante"},{"name":"café"},{"name":"effectuer"},{"name":"indiquer"},{"name":"réunir"},{"name":"panda"},{"name":"patriote"},{"name":"poussin"},{"name":"vieillesse"},{"name":"ronger"},{"name":"principalement"},{"name":"favori"},{"name":"contenir"},{"name":"lumière"},{"name":"élever"},{"name":"pavillon"},{"name":"façade"},{"name":"métal"},{"name":"usine"},{"name":"retraite"},{"name":"fraction"},{"name":"calice"},{"name":"subir"},{"name":"ajouter"},{"name":"raccommoder"},{"name":"printanier"},{"name":"refléter"},{"name":"repas"},{"name":"forme"},{"name":"joint"},{"name":"allié"},{"name":"vilain"},{"name":"grappe"},{"name":"violemment"},{"name":"linge"},{"name":"fragile"},{"name":"aboutir"},{"name":"fardeau"},{"name":"mouchoir"},{"name":"masse"},{"name":"commandant"},{"name":"propice"},{"name":"motif"},{"name":"uniquement"},{"name":"étudier"},{"name":"laver"},{"name":"charrette"},{"name":"saisissant"},{"name":"oreille"},{"name":"marron"},{"name":"terme"},{"name":"soif"},{"name":"huit"},{"name":"alors"},{"name":"défenseur"},{"name":"soir"},{"name":"grimace"},{"name":"presser"},{"name":"hiver"},{"name":"juge"},{"name":"traitement"},{"name":"former"},{"name":"vide"},{"name":"route"},{"name":"quartier"},{"name":"grain"},{"name":"tissu"},{"name":"pâlir"},{"name":"compassion"},{"name":"abandonner"},{"name":"différence"},{"name":"vin"},{"name":"difficile"},{"name":"coucher"},{"name":"couche"},{"name":"terrasse"},{"name":"illustre"},{"name":"étincelle"},{"name":"malade"},{"name":"pli"},{"name":"riant"},{"name":"estrade"},{"name":"sifflement"},{"name":"douceur"},{"name":"ours"},{"name":"discuter"},{"name":"coiffure"},{"name":"monter"},{"name":"bâton"},{"name":"garde"},{"name":"habile"},{"name":"sourire"},{"name":"peur"},{"name":"berceau"},{"name":"Noël"},{"name":"tiède"},{"name":"gravier"},{"name":"fou"},{"name":"prévenir"},{"name":"après"},{"name":"volontiers"},{"name":"pot"},{"name":"librement"},{"name":"douleur"},{"name":"souper"},{"name":"lapin"},{"name":"habiller"},{"name":"déposer"},{"name":"bondir"},{"name":"fréquenter"},{"name":"sûr"},{"name":"télégramme"},{"name":"pompe"},{"name":"rossignol"},{"name":"attente"},{"name":"pas"},{"name":"dérober"},{"name":"jeunesse"},{"name":"patron"},{"name":"gaiement"},{"name":"vérité"},{"name":"manger"},{"name":"vivement"},{"name":"haillons"},{"name":"journaliste"},{"name":"climat"},{"name":"cirque"},{"name":"second"},{"name":"regard"},{"name":"amplitude"},{"name":"actuel"},{"name":"sergent"},{"name":"dresser"},{"name":"couture"},{"name":"sale"},{"name":"tronc"},{"name":"monotone"},{"name":"farouche"},{"name":"tuile"},{"name":"salle"},{"name":"écharpe"},{"name":"foudre"},{"name":"amour"},{"name":"net"},{"name":"pré"},{"name":"septembre"},{"name":"alouette"},{"name":"banque"},{"name":"céder"},{"name":"avantageux"},{"name":"partout"},{"name":"marbre"},{"name":"impatience"},{"name":"enfuir"},{"name":"refrain"},{"name":"cabinet"},{"name":"poignard"},{"name":"tricoter"},{"name":"matériaux"},{"name":"consacrer"},{"name":"libraire"},{"name":"plupart"},{"name":"corbeille"},{"name":"jaloux"},{"name":"velours"},{"name":"éclairer"},{"name":"sable"},{"name":"joue"},{"name":"crier"},{"name":"aisance"},{"name":"poème"},{"name":"infini"},{"name":"cuisinier"},{"name":"obtenir"},{"name":"brillant"},{"name":"indien"},{"name":"céleste"},{"name":"double"},{"name":"opinion"},{"name":"continuellement"},{"name":"apprendre"},{"name":"langage"},{"name":"cheval"},{"name":"dépasser"},{"name":"sifflet"},{"name":"gai"},{"name":"emploi"},{"name":"industrie"},{"name":"fusil"},{"name":"mélancolique"},{"name":"magasin"},{"name":"bosquet"},{"name":"plaque"},{"name":"absent"},{"name":"reconduire"},{"name":"four"},{"name":"herbe"},{"name":"canot"},{"name":"varier"},{"name":"déchirer"},{"name":"droite"},{"name":"manier"},{"name":"armoire"},{"name":"marteau"},{"name":"labourer"},{"name":"délicat"},{"name":"tigre"},{"name":"refroidir"},{"name":"intérêt"},{"name":"forêt"},{"name":"ouvrage"},{"name":"pâtre"},{"name":"luisant"},{"name":"pencher"},{"name":"de"},{"name":"silencieusement"},{"name":"solution"},{"name":"palais"},{"name":"hameau"},{"name":"pourvoir"},{"name":"côté"},{"name":"moqueur"},{"name":"affamé"},{"name":"farine"},{"name":"paresseux"},{"name":"décision"},{"name":"affaire"},{"name":"gauche"},{"name":"million"},{"name":"coupure"},{"name":"cueillette"},{"name":"commerçant"},{"name":"habitude"},{"name":"maintenant"},{"name":"viande"},{"name":"décorer"},{"name":"laie"},{"name":"conter"},{"name":"cigare"},{"name":"commencer"},{"name":"immédiat"},{"name":"soustraction"},{"name":"morceau"},{"name":"copie"},{"name":"chanson"},{"name":"autrefois"},{"name":"tapage"},{"name":"insecte"},{"name":"meuble"},{"name":"souris"},{"name":"hors"},{"name":"plancher"},{"name":"adresse"},{"name":"fauteuil"},{"name":"concours"},{"name":"bonté"},{"name":"cents"},{"name":"voir"},{"name":"surveillant"},{"name":"catastrophe"},{"name":"échec"},{"name":"avaler"},{"name":"étouffant"},{"name":"soumettre"},{"name":"matin"},{"name":"métier"},{"name":"couronne"},{"name":"inspirer"},{"name":"royal"},{"name":"successivement"},{"name":"souci"},{"name":"combien"},{"name":"adroit"},{"name":"admiration"},{"name":"obus"},{"name":"hésitant"},{"name":"art"},{"name":"instituteur"},{"name":"attirer"},{"name":"différence"},{"name":"hui"},{"name":"mou"},{"name":"précieux"},{"name":"offensive"},{"name":"lentement"},{"name":"deviner"},{"name":"démarche"},{"name":"possibilité"},{"name":"copain"},{"name":"octobre"},{"name":"visible"},{"name":"éviter"},{"name":"troisième"},{"name":"pomme"},{"name":"voyageur"},{"name":"épais"},{"name":"logement"},{"name":"docile"},{"name":"juste"},{"name":"chétif"},{"name":"arrondissement"},{"name":"acquérir"},{"name":"position"},{"name":"piano"},{"name":"pleuvoir"},{"name":"convenable"},{"name":"pratiquer"},{"name":"injuste"},{"name":"piscine"},{"name":"résistance"},{"name":"produit"},{"name":"montagne"},{"name":"pâquerette"},{"name":"observer"},{"name":"figurer"},{"name":"bois"},{"name":"faner"},{"name":"serviette"},{"name":"bec"},{"name":"monter"},{"name":"effort"},{"name":"tablier"},{"name":"lors"},{"name":"vif"},{"name":"immeuble"},{"name":"couper"},{"name":"respecter"},{"name":"halte"},{"name":"habituer"},{"name":"continuellement"},{"name":"montant"},{"name":"honnêteté"},{"name":"balayer"},{"name":"oreiller"},{"name":"abeille"},{"name":"cachette"},{"name":"cortège"},{"name":"éclairage"},{"name":"île"},{"name":"congrès"},{"name":"immédiatement"},{"name":"prison"},{"name":"vapeur"},{"name":"arrivée"},{"name":"chaussure"},{"name":"présider"},{"name":"prudent"},{"name":"triste"},{"name":"égayer"},{"name":"paysage"},{"name":"soupe"},{"name":"tombe"},{"name":"supplier"},{"name":"inférieur"},{"name":"intention"},{"name":"règlement"},{"name":"honte"},{"name":"parquet"},{"name":"réponse"},{"name":"ciel"},{"name":"ramper"},{"name":"logis"},{"name":"Pâques"},{"name":"fatal"},{"name":"creuser"},{"name":"réparation"},{"name":"transformation"},{"name":"tacher"},{"name":"glisser"},{"name":"raison"},{"name":"ressembler"},{"name":"penser"},{"name":"commode"},{"name":"fumer"},{"name":"regarder"},{"name":"dispute"},{"name":"matinée"},{"name":"dividende"},{"name":"farce"},{"name":"chariot"},{"name":"apprécier"},{"name":"communication"},{"name":"taper"},{"name":"jambe"},{"name":"boulevard"},{"name":"témoignage"},{"name":"maison"},{"name":"munir"},{"name":"plumage"},{"name":"treize"},{"name":"surprise"},{"name":"agrément"},{"name":"responsable"},{"name":"rafraîchir"},{"name":"groupe"},{"name":"police"},{"name":"fatigue"},{"name":"pétrole"},{"name":"pic"},{"name":"vestibule"},{"name":"volonté"},{"name":"satisfaisant"}]